mafm/__init__.py
mafm/bin/SuSiEx
mafm/bin/finemap
mafm/cli.py
mafm/cojo.py
mafm/constants.py
mafm/credibleset.py
mafm/ldmatrix.py
mafm/locus.py
mafm/mafm.py
mafm/meta.py
mafm/qc.py
mafm/sumstats.py
mafm/utils.py
mafm/web/README.md
mafm/web/__init__.py
mafm/web/app.py
mafm/web/export.py
mafm/web/pages/__init__.py
mafm/web/pages/home.py
mafm/web/pages/locus.py
mafm/wrappers/RSparsePro.py
mafm/wrappers/__init__.py
mafm/wrappers/abf.py
mafm/wrappers/carma.py
mafm/wrappers/finemap.py
mafm/wrappers/multisusie.py
mafm/wrappers/multisusie_rss.py
mafm/wrappers/susie.py
mafm/wrappers/susie_rss.py
mafm/wrappers/susiex.py
mafm-0.0.27.dist-info/LICENSE
mafm-0.0.27.dist-info/METADATA
mafm-0.0.27.dist-info/WHEEL
mafm-0.0.27.dist-info/entry_points.txt
mafm-0.0.27.dist-info/RECORD
