Metadata-Version: 2.3
Name: mafm
Version: 0.0.27
Summary: multi-ancestry fine-mapping pipeline.
License: MIT
Author: Jianhua Wang
Author-email: jianhua.mert@gmail.com
Requires-Python: >=3.9,<3.13
Classifier: Development Status :: 2 - Pre-Alpha
Classifier: Intended Audience :: Developers
Classifier: License :: OSI Approved :: MIT License
Classifier: Natural Language :: English
Classifier: Programming Language :: Python :: 3
Classifier: Programming Language :: Python :: 3.9
Classifier: Programming Language :: Python :: 3.10
Classifier: Programming Language :: Python :: 3.11
Classifier: Programming Language :: Python :: 3.12
Provides-Extra: web
Requires-Dist: cojopy (==0.1.2)
Requires-Dist: dash (>=2.10.0) ; extra == "web"
Requires-Dist: dash-bootstrap-components (>=1.4.0) ; extra == "web"
Requires-Dist: dash-mantine-components (>=0.12.0) ; extra == "web"
Requires-Dist: matplotlib (>=3.9.2)
Requires-Dist: numba (>=0.60.0,<0.61.0)
Requires-Dist: numpy (>=1.21.2)
Requires-Dist: pandas (>=1.3.3)
Requires-Dist: plotly (>=5.14.0) ; extra == "web"
Requires-Dist: rich (>=12.4.0)
Requires-Dist: rpy2 (>=3.5.16,<4.0.0)
Requires-Dist: scikit-learn (>=1.5.2)
Requires-Dist: scipy (>=1.7.3)
Requires-Dist: tqdm (>=4.66.5,<5.0.0)
Requires-Dist: typer (>=0.7.0)
Project-URL: Homepage, https://github.com/Jianhua-Wang/mafm
